{"statistical_data": {"friends_num": 12, "active_num": 5, "error_num": 7, "article_num": 18, "last_updated_time": "2023-12-17 02:07:49"}, "article_data": [{"floor": 1, "title": "\u541b\u306e\u3053\u3068\u304c\u5927\u5927\u5927\u5927\u5927\u597d\u304d\u306a100\u4eba\u306e\u5f7c\u5973\uff5c\u8d85\u8d85\u8d85\u8d85\u559c\u6b22\u4f60\u7684100\u4e2a\u5973\u5b69\u5b50\uff5c\u8d85\u8d85\u8d85\u8d85\u8d85\u559c\u6b61\u4f60\u7684100\u500b\u5973\u670b\u53cb\uff5c\u8d85\u8d85\u8d85\u8d85\u8d85\u559c\u6b61\u4f60\u7684 100 \u500b\u5973\u670b\u53cb", "created": "2023-12-17", "updated": "2023-12-17", "link": "https://rssbox.imc.re/RSSBOX/rss/d4954920.html", "author": "RSSBOX", "avatar": "https://rssbox.imc.re/avatar.png"}, {"floor": 2, "title": "\u3067\u3053\u307c\u3053\u9b54\u5973\u306e\u89aa\u5b50\u4e8b\u60c5\uff5c\u51f9\u51f8\u9b54\u5973\u7684\u6bcd\u5973\u6545\u4e8b\uff5c\u51f9\u51f8\u9b54\u5973\u7684\u89aa\u5b50\u65e5\u5e38\uff5c\u51f9\u51f8\u9b54\u5973\u7684\u89aa\u5b50\u65e5\u5e38\uff5cThe Family Circumstances of the Imbalanced Witch", "created": "2023-12-17", "updated": "2023-12-17", "link": "https://rssbox.imc.re/RSSBOX/rss/c030eb6e.html", "author": "RSSBOX", "avatar": "https://rssbox.imc.re/avatar.png"}, {"floor": 3, "title": "\u30aa\u30fc\u30d0\u30fc\u30c6\u30a4\u30af\uff01\uff5cOvertake!\uff5cOvertake!", "created": "2023-12-17", "updated": "2023-12-17", "link": "https://rssbox.imc.re/RSSBOX/rss/22d8813b.html", "author": "RSSBOX", "avatar": "https://rssbox.imc.re/avatar.png"}, {"floor": 4, "title": "\u30ad\u30e3\u30d7\u30c6\u30f3\u7ffc\u30b7\u30fc\u30ba\u30f32 \u30b8\u30e5\u30cb\u30a2\u30e6\u30fc\u30b9\u7de8\uff5c\u8db3\u7403\u5c0f\u5c06 \u7b2c\u4e8c\u5b63 \u4e16\u5c11\u7bc7\uff5c\u968a\u9577\u5c0f\u7ffc\u7b2c\u4e8c\u5b63 \u9752\u5c11\u5e74\u7bc7\uff5c\u968a\u9577\u5c0f\u7ffc Season2 \u9752\u5c11\u5e74\u7bc7", "created": "2023-12-17", "updated": "2023-12-17", "link": "https://rssbox.imc.re/RSSBOX/rss/1a0ce0a8.html", "author": "RSSBOX", "avatar": "https://rssbox.imc.re/avatar.png"}, {"floor": 5, "title": "\u30b7\u30e3\u30f3\u30b0\u30ea\u30e9\u30fb\u30d5\u30ed\u30f3\u30c6\u30a3\u30a2\uff5e\u30af\u30bd\u30b2\u30fc\u30cf\u30f3\u30bf\u30fc\u3001\u795e\u30b2\u30fc\u306b\u6311\u307e\u3093\u3068\u3059\uff5e\uff5c\u9999\u683c\u91cc\u62c9\u00b7\u5f17\u9647\u63d0\u4e9a\uff5e\u5c4e\u4f5c\u730e\u4eba\u5411\u795e\u4f5c\u53d1\u8d77\u6311\u6218\uff5e\uff5c\u9999\u683c\u91cc\u62c9\u8fb9\u5883~\u7caa\u4f5c\u730e\u4eba\u5411\u795e\u4f5c\u6e38\u620f\u53d1\u8d77...", "created": "2023-12-17", "updated": "2023-12-17", "link": "https://rssbox.imc.re/RSSBOX/rss/fd1e5ec9.html", "author": "RSSBOX", "avatar": "https://rssbox.imc.re/avatar.png"}, {"floor": 6, "title": "\u30c9\u30c3\u30b0\u30b7\u30b0\u30ca\u30eb\uff5c\u7231\u72ac\u6307\u4ee4\uff5c\u611b\u72ac\u8a0a\u865f\uff5cDOG SIGNAL", "created": "2023-12-17", "updated": "2023-12-17", "link": "https://blog.imc.re/RSSBOX/rss/d34e2206.html", "author": "RSSBOX", "avatar": "https://rssbox.imc.re/avatar.png"}, {"floor": 7, "title": "The Touhou Empires", "created": "2023-12-16", "updated": "2023-12-16", "link": "https://touhou.pub/rss/1f972eaf.html", "author": "Touhou.Pub", "avatar": "https://touhou.pub/assets/logo/touhou_lite_color.svg"}, {"floor": 8, "title": "Touhou Crisis", "created": "2023-12-16", "updated": "2023-12-16", "link": "https://touhou.pub/rss/1e67efb1.html", "author": "Touhou.Pub", "avatar": "https://touhou.pub/assets/logo/touhou_lite_color.svg"}, {"floor": 9, "title": "Touhou DollDraft", "created": "2023-12-16", "updated": "2023-12-16", "link": "https://touhou.pub/rss/bebdd4ea.html", "author": "Touhou.Pub", "avatar": "https://touhou.pub/assets/logo/touhou_lite_color.svg"}, {"floor": 10, "title": "Touhou Fantasia / \u4e1c\u65b9\u68a6\u60f3\u66f2", "created": "2023-12-16", "updated": "2023-12-16", "link": "https://touhou.pub/rss/dfe5e379.html", "author": "Touhou.Pub", "avatar": "https://touhou.pub/assets/logo/touhou_lite_color.svg"}, {"floor": 11, "title": "Touhou Fractured Transience", "created": "2023-12-16", "updated": "2023-12-16", "link": "https://touhou.pub/rss/93f58688.html", "author": "Touhou.Pub", "avatar": "https://touhou.pub/assets/logo/touhou_lite_color.svg"}, {"floor": 12, "title": "Touhou Gensokyo Visitor", "created": "2023-12-16", "updated": "2023-12-16", "link": "https://touhou.pub/rss/f7adfb0a.html", "author": "Touhou.Pub", "avatar": "https://touhou.pub/assets/logo/touhou_lite_color.svg"}, {"floor": 13, "title": "\u82f9\u679c\u8bbe\u8ba1\u7d20\u6750\u5b98\u65b9\u4e0b\u8f7d\u5730\u5740", "created": "2023-12-13", "updated": "2023-12-13", "link": "https://xaoxuu.com/blog/20231213/", "author": "XAOXUU", "avatar": "https://bu.dusays.com/2021/09/24/2f74810ceb3d3.png"}, {"floor": 14, "title": "\u4e2d\u61671+X\u8bc1\u4e66\u771f\u9898", "created": "2023-10-31", "updated": "2023-10-31", "link": "https://blog.imc.re/archives/7daf.html", "author": "IMC.RE \u4e3b\u9875", "avatar": "https://cdn.jsdelivr.net/gh/SMGCDN/photos/logo/imc.re_x512.png"}, {"floor": 15, "title": "\u4e2d\u61671+X\u8bc1\u4e66\u9898\u5e93", "created": "2023-10-31", "updated": "2023-10-31", "link": "https://blog.imc.re/archives/260d.html", "author": "IMC.RE \u4e3b\u9875", "avatar": "https://cdn.jsdelivr.net/gh/SMGCDN/photos/logo/imc.re_x512.png"}, {"floor": 16, "title": "kafka\u5b89\u88c5\u6587\u6863", "created": "2023-10-24", "updated": "2023-10-24", "link": "https://blog.imc.re/archives/kafka.html", "author": "IMC.RE \u4e3b\u9875", "avatar": "https://cdn.jsdelivr.net/gh/SMGCDN/photos/logo/imc.re_x512.png"}, {"floor": 17, "title": "zookeeper\u5b89\u88c5\u6587\u6863", "created": "2023-10-24", "updated": "2023-10-24", "link": "https://blog.imc.re/archives/zookeeper.html", "author": "IMC.RE \u4e3b\u9875", "avatar": "https://cdn.jsdelivr.net/gh/SMGCDN/photos/logo/imc.re_x512.png"}, {"floor": 18, "title": "MCBE 88\u97f3\u5e73\u5747\u5f8b", "created": "2023-05-14", "updated": "2023-10-31", "link": "http://blog.imc.re/archives/7d13.html", "author": "IMC.RE \u4e3b\u9875", "avatar": "https://cdn.jsdelivr.net/gh/SMGCDN/photos/logo/imc.re_x512.png"}]}