{"statistical_data": {"friends_num": 12, "active_num": 5, "error_num": 7, "article_num": 12, "last_updated_time": "2023-10-05 14:08:36"}, "article_data": [{"floor": 1, "title": "\u30d3\u30c3\u30af\u30ea\u30e1\u30f3\uff5cBIKKURI-MEN\uff5c\u4ed9\u9b54\u5927\u6218", "created": "2023-10-05", "updated": "2023-10-05", "link": "https://rssbox.imc.re/RSSBOX/rss/5bb1da5e.html", "author": "RSSBOX", "avatar": "https://rssbox.imc.re/avatar.png"}, {"floor": 2, "title": "\u67da\u6728\u3055\u3093\u3061\u306e\u56db\u5144\u5f1f\u3002\uff5c\u67da\u6728\u5bb6\u7684\u56db\u5144\u5f1f\u3002", "created": "2023-10-05", "updated": "2023-10-05", "link": "https://rssbox.imc.re/RSSBOX/rss/a11b7ef8.html", "author": "RSSBOX", "avatar": "https://rssbox.imc.re/avatar.png"}, {"floor": 3, "title": "Adoration of the Palm Trees", "created": "2023-10-05", "updated": "2023-10-05", "link": "https://rssbox.imc.re/RSSBOX/rss/eeac494d.html", "author": "RSSBOX", "avatar": "https://rssbox.imc.re/avatar.png"}, {"floor": 4, "title": "Beasts Bounding Through Time", "created": "2023-10-05", "updated": "2023-10-05", "link": "https://rssbox.imc.re/RSSBOX/rss/2c89ff60.html", "author": "RSSBOX", "avatar": "https://rssbox.imc.re/avatar.png"}, {"floor": 5, "title": "Bye-Child", "created": "2023-10-05", "updated": "2023-10-05", "link": "https://rssbox.imc.re/RSSBOX/rss/e29e4c0e.html", "author": "RSSBOX", "avatar": "https://rssbox.imc.re/avatar.png"}, {"floor": 6, "title": "Love Is Not All", "created": "2023-10-05", "updated": "2023-10-05", "link": "https://blog.imc.re/RSSBOX/rss/41fdd8ae.html", "author": "RSSBOX", "avatar": "https://rssbox.imc.re/avatar.png"}, {"floor": 7, "title": "The Touhou Empires", "created": "2023-10-05", "updated": "2023-10-05", "link": "https://touhou.pub/rss/1f972eaf.html", "author": "Touhou.Pub", "avatar": "https://touhou.pub/assets/logo/touhou_lite_color.svg"}, {"floor": 8, "title": "Touhou Artificial Dream in Arcadia", "created": "2023-10-05", "updated": "2023-10-05", "link": "https://touhou.pub/rss/b4ecdfec.html", "author": "Touhou.Pub", "avatar": "https://touhou.pub/assets/logo/touhou_lite_color.svg"}, {"floor": 9, "title": "Touhou Crisis", "created": "2023-10-05", "updated": "2023-10-05", "link": "https://touhou.pub/rss/1e67efb1.html", "author": "Touhou.Pub", "avatar": "https://touhou.pub/assets/logo/touhou_lite_color.svg"}, {"floor": 10, "title": "Touhou DollDraft", "created": "2023-10-05", "updated": "2023-10-05", "link": "https://touhou.pub/rss/bebdd4ea.html", "author": "Touhou.Pub", "avatar": "https://touhou.pub/assets/logo/touhou_lite_color.svg"}, {"floor": 11, "title": "Touhou Fantasia / \u4e1c\u65b9\u68a6\u60f3\u66f2", "created": "2023-10-05", "updated": "2023-10-05", "link": "https://touhou.pub/rss/dfe5e379.html", "author": "Touhou.Pub", "avatar": "https://touhou.pub/assets/logo/touhou_lite_color.svg"}, {"floor": 12, "title": "Touhou Fractured Transience", "created": "2023-10-05", "updated": "2023-10-05", "link": "https://touhou.pub/rss/93f58688.html", "author": "Touhou.Pub", "avatar": "https://touhou.pub/assets/logo/touhou_lite_color.svg"}]}